ddclassification/__init__.py
ddclassification/lip_reading/__init__.py
ddclassification/lip_reading/model/__init__.py
ddclassification/lip_reading/model/lstm_5.py
ddclassification/lip_reading/utils/__init__.py
ddclassification/lip_reading/utils/method.py
ddclassification/utils/__init__.py
ddclassification/utils/data_generator.py
ddclassification-0.1.3.dist-info/LICENSE
ddclassification-0.1.3.dist-info/METADATA
ddclassification-0.1.3.dist-info/WHEEL
ddclassification-0.1.3.dist-info/top_level.txt
ddclassification-0.1.3.dist-info/RECORD
